unzipall/__init__.py
unzipall/cli.py
unzipall/core.py
unzipall/exceptions.py
unzipall-1.0.1.dist-info/licenses/LICENSE
unzipall-1.0.1.dist-info/METADATA
unzipall-1.0.1.dist-info/WHEEL
unzipall-1.0.1.dist-info/entry_points.txt
unzipall-1.0.1.dist-info/top_level.txt
unzipall-1.0.1.dist-info/RECORD
