Metadata-Version: 2.4
Name: unzipall
Version: 1.0.1
Summary: Universal archive extractor supporting 30+ formats including ZIP, RAR, 7Z, TAR, and many more
Author-email: mricardo <ricardo.lee.cm@gmail.com>
Maintainer-email: mricardo <ricardo.lee.cm@gmail.com>
License: MIT
Project-URL: Homepage, https://github.com/mricardo/unzipall
Project-URL: Repository, https://github.com/mricardo/unzipall
Project-URL: Documentation, https://github.com/mricardo/unzipall#readme
Project-URL: Bug Tracker, https://github.com/mricardo/unzipall/issues
Project-URL: Funding, https://github.com/sponsors/mricardo
Keywords: archive,extract,zip,rar,7z,tar,compression,unzip,extractor,decompress,unpack,universal
Classifier: Development Status :: 5 - Production/Stable
Classifier: Intended Audience :: Developers
Classifier: Intended Audience :: System Administrators
Classifier: Intended Audience :: End Users/Desktop
Classifier: License :: OSI Approved :: MIT License
Classifier: Programming Language :: Python :: 3
Classifier: Programming Language :: Python :: 3.8
Classifier: Programming Language :: Python :: 3.9
Classifier: Programming Language :: Python :: 3.10
Classifier: Programming Language :: Python :: 3.11
Classifier: Programming Language :: Python :: 3.12
Classifier: Topic :: System :: Archiving :: Compression
Classifier: Topic :: System :: Systems Administration
Classifier: Topic :: Utilities
Classifier: Operating System :: OS Independent
Classifier: Operating System :: Microsoft :: Windows
Classifier: Operating System :: POSIX :: Linux
Classifier: Operating System :: MacOS
Classifier: Environment :: Console
Classifier: Typing :: Typed
Requires-Python: >=3.8
License-File: LICENSE
Requires-Dist: py7zr>=0.20.0
Requires-Dist: rarfile>=4.0
Requires-Dist: patool>=1.12.0
Requires-Dist: libarchive-c>=4.0
Requires-Dist: python-magic>=0.4.27; sys_platform != "win32"
Requires-Dist: python-magic-bin>=0.4.14; sys_platform == "win32"
Requires-Dist: pycdlib>=1.13.0
Provides-Extra: iso
Requires-Dist: pycdlib>=1.13.0; extra == "iso"
Provides-Extra: advanced
Requires-Dist: patool>=1.12.0; extra == "advanced"
Requires-Dist: libarchive-c>=4.0; extra == "advanced"
Provides-Extra: all
Requires-Dist: unzipall[advanced,iso]; extra == "all"
Provides-Extra: dev
Requires-Dist: pytest>=7.0; extra == "dev"
Requires-Dist: pytest-cov>=4.0; extra == "dev"
Requires-Dist: pytest-mock>=3.10.0; extra == "dev"
Requires-Dist: black>=22.0; extra == "dev"
Requires-Dist: flake8>=5.0; extra == "dev"
Requires-Dist: mypy>=1.0; extra == "dev"
Requires-Dist: pre-commit>=2.20; extra == "dev"
Requires-Dist: twine>=4.0; extra == "dev"
Requires-Dist: build>=0.8.0; extra == "dev"
Provides-Extra: docs
Requires-Dist: mkdocs>=1.4; extra == "docs"
Requires-Dist: mkdocs-material>=8.5; extra == "docs"
Requires-Dist: mkdocs-mermaid2-plugin>=0.6.0; extra == "docs"
Provides-Extra: test-full
Requires-Dist: unzipall[all,dev]; extra == "test-full"
Requires-Dist: pytest-xdist>=3.0; extra == "test-full"
Requires-Dist: pytest-benchmark>=4.0; extra == "test-full"
Dynamic: license-file
